{
    "dogecoin": [
        {
            "tweet_count": 1,
            "username": "Simp👽",
            "user_account": "theXderation",
            "text": "What are the new top meme coins?\n\n$DOGE\n$PEPE\n$JESUS\n\nWhat else??",
            "created_at": "Sat May 11 23:57:15 +0000 2024",
            "retweet": 0,
            "likes": 9,
            "retweeted_tweet": null
        },
        {
            "tweet_count": 2,
            "username": "Mr. New_Whale",
            "user_account": "TheNewWhale_",
            "text": "🔴2013 - You missed $BTC\n🔴 2014 - You missed $DOGE\n🔴 2015 - You missed $XRP\n🔴 2016 - You missed $ETH\n🔴 2017 - You missed $ADA\n🔴 2018 - You missed $BNB\n🔴 2019 - You missed $LINK\n🔴 2020 - You missed $DOT\n🔴 2021 - You missed $SHIB\n🟢 In 2024, don't miss $AYBAI\n@AyyubsAltun",
            "created_at": "Sat May 11 23:55:39 +0000 2024",
            "retweet": 2,
            "likes": 3,
            "retweeted_tweet": null
        },
        {
            "tweet_count": 3,
            "username": "Manuel 🇻🇪",
            "user_account": "mani05_",
            "text": "i need a dogecoin",
            "created_at": "Sat May 11 23:51:52 +0000 2024",
            "retweet": 0,
            "likes": 0,
            "retweeted_tweet": null
        },
        {
            "tweet_count": 4,
            "username": "Sir Herk 🧬🐾🐾",
            "user_account": "Spacedogoxyz",
            "text": "Greetings....it's a very #dogecoin sunset https://t.co/8nTg9pIwyq",
            "created_at": "Sat May 11 23:51:38 +0000 2024",
            "retweet": 0,
            "likes": 2,
            "retweeted_tweet": null
        },
        {
            "tweet_count": 5,
            "username": "Brave Legacy 🐦‍🔥",
            "user_account": "EdLegacy777",
            "text": "@cryptocom Buy $FFTB\nSell $DOGE\nHodl $CRO",
            "created_at": "Sat May 11 23:51:31 +0000 2024",
            "retweet": 0,
            "likes": 1,
            "retweeted_tweet": null
        },
        {
            "tweet_count": 6,
            "username": "BTCBrendan",
            "user_account": "BTC_Brendan",
            "text": "$DOGE dropping to $0.1058 has a lot of confluence rn ngl",
            "created_at": "Sat May 11 23:51:24 +0000 2024",
            "retweet": 0,
            "likes": 0,
            "retweeted_tweet": null
        },
        {
            "tweet_count": 7,
            "username": "Andrew Newman",
            "user_account": "XRPeclipse",
            "text": "@WhaleFUD It’s 2024, we still talking about dogecoin?",
            "created_at": "Sat May 11 23:51:05 +0000 2024",
            "retweet": 0,
            "likes": 5,
            "retweeted_tweet": null
        },
        {
            "tweet_count": 8,
            "username": "@sage",
            "user_account": "SagevsBabylon",
            "text": "@WhaleFUD You can guarantee if Elon makes it to Mars before he dies, Dogecoin will be the first currency used for a transaction",
            "created_at": "Sat May 11 23:50:44 +0000 2024",
            "retweet": 0,
            "likes": 0,
            "retweeted_tweet": null
        },
        {
            "tweet_count": 9,
            "username": "Curious Doge",
            "user_account": "curious_doge_",
            "text": "@tjstebbing Dogecoin is the best example of this combination of nostalgia and futurism\n\nIt's an archaic revival of the best qualities of the old Internet—wholesome, decentralized, retro aesthetics, embrace of quirk and weirdness—welded to cutting edge blockchain tech for a better tomorrow🚀",
            "created_at": "Sat May 11 23:49:38 +0000 2024",
            "retweet": 0,
            "likes": 0,
            "retweeted_tweet": null
        },
        {
            "tweet_count": 10,
            "username": "Heely ~ Clever 🦊",
            "user_account": "HookedOnAHeelin",
            "text": "@ChildOfTheLostt @vamqzi sugar daddy, sugar mommy, my account is hacked, doge coin, e currency, NFT, help!, broke,",
            "created_at": "Sat May 11 23:48:19 +0000 2024",
            "retweet": 0,
            "likes": 3,
            "retweeted_tweet": null
        },
        {
            "tweet_count": 11,
            "username": "frohzd",
            "user_account": "FrOHzD",
            "text": "Wanna see some funny shit?\n\nGo look at the monthly chart on $PEPE 🐸\n\nThen look at the monthly chart on shiba inu and doge coin 🤣😂\n\nPretty obvious the whales are loading\n\nThe meme coin rotation has begun\n\n🐕➡️🐸 https://t.co/dI2rdsUoOe",
            "created_at": "Sat May 11 23:47:53 +0000 2024",
            "retweet": 6,
            "likes": 60,
            "retweeted_tweet": null
        },
        {
            "tweet_count": 12,
            "username": "WF",
            "user_account": "WhaleFUD",
            "text": "JUST IN:\n\nElon Musk said he still owns a bunch of Dogecoin",
            "created_at": "Sat May 11 23:47:07 +0000 2024",
            "retweet": 124,
            "likes": 1023,
            "retweeted_tweet": null
        },
        {
            "tweet_count": 13,
            "username": "Tony",
            "user_account": "Tony4_19",
            "text": "@mistressdivy When moon? Dogecoin",
            "created_at": "Sat May 11 23:45:27 +0000 2024",
            "retweet": 0,
            "likes": 2,
            "retweeted_tweet": null
        },
        {
            "tweet_count": 14,
            "username": "Elizabeth Hoigaard",
            "user_account": "hoigaardlizzy",
            "text": "@cb_doge What is a Doge coin?  Is that the equivalent of me giving my Amex to my kid and telling him to go buy me a Mother’s Day present before the stores close Saturday evening? 🤣",
            "created_at": "Sat May 11 23:43:59 +0000 2024",
            "retweet": 0,
            "likes": 0,
            "retweeted_tweet": null
        },
        {
            "tweet_count": 15,
            "username": "LuisCarvalho",
            "user_account": "luishencrvalho",
            "text": "@Oppie_Robert It’s $DOG, not $DOGE",
            "created_at": "Sat May 11 23:43:16 +0000 2024",
            "retweet": 1,
            "likes": 1,
            "retweeted_tweet": null
        },
        {
            "tweet_count": 16,
            "username": "Tritano",
            "user_account": "trincalco",
            "text": "@munky_on_sol Munky will kill all $wif $pepe $doge $shiba",
            "created_at": "Sat May 11 23:42:45 +0000 2024",
            "retweet": 0,
            "likes": 0,
            "retweeted_tweet": null
        },
        {
            "tweet_count": 17,
            "username": "SolFoMo",
            "user_account": "ProphetVision",
            "text": "@mcJoker_05 @dom_lucre @barrtremp_sol Of all the Politifi meme, $Barr has the strongest and most long term narrative, patience is key!! Just like buying $btc and $doge in early years!! \n\n$boden $tremp $tooker $michi $jowens $kenidy",
            "created_at": "Sat May 11 23:42:41 +0000 2024",
            "retweet": 0,
            "likes": 2,
            "retweeted_tweet": null
        },
        {
            "tweet_count": 18,
            "username": "CRYPTO IS MY RETIREMENT - #CIMR",
            "user_account": "KINGHARRYIII",
            "text": "Dogechain  🌶️ Chili House now open…\n\nReal Hustler’s - Real Degan - Real 🌶️ \n\n$DC - $Omnom - $DINU - $Dbit - $Doge \n\nhttps://t.co/VIG7GDCpyk\n\n🚀👀🌶️😎 https://t.co/7K9stDp2rz",
            "created_at": "Sat May 11 23:41:32 +0000 2024",
            "retweet": 2,
            "likes": 9,
            "retweeted_tweet": null
        },
        {
            "tweet_count": 19,
            "username": "Ms_Independent❤️",
            "user_account": "ripebelly",
            "text": "@cb_doge Doge coin failed me!",
            "created_at": "Sat May 11 23:38:22 +0000 2024",
            "retweet": 0,
            "likes": 0,
            "retweeted_tweet": null
        },
        {
            "tweet_count": 20,
            "username": "Casey Mize Apologist",
            "user_account": "Pistons_Cade",
            "text": "@GREEAR10 Not the guy with dogecoin and a game of thrones banner on his Twitter page being the authority on what's gay 💀 brother you clearly are a massive fan of a show that is 50% screen time for other men's junk",
            "created_at": "Sat May 11 23:34:34 +0000 2024",
            "retweet": 0,
            "likes": 0,
            "retweeted_tweet": null
        },
        {
            "tweet_count": 21,
            "username": "Twinkle Twat",
            "user_account": "GlitterDoggess",
            "text": "Have a magical Saturday night\nX fam 🫶\nDogecoin✨ https://t.co/qYeXuzh5Gt",
            "created_at": "Sat May 11 23:34:34 +0000 2024",
            "retweet": 2,
            "likes": 22,
            "retweeted_tweet": null
        },
        {
            "tweet_count": 22,
            "username": "Neil",
            "user_account": "Neil2000h",
            "text": "@JustinScerini He’s cooking no one! The fact he’s even wasting his time with this joke of a case has got to be the prime of his career. I stopped dogecoin lol 😂",
            "created_at": "Sat May 11 23:33:04 +0000 2024",
            "retweet": 0,
            "likes": 0,
            "retweeted_tweet": null
        },
        {
            "tweet_count": 23,
            "username": "fity.eth",
            "user_account": "Fityeth",
            "text": "@DaddyD3G3N @polaonbase ok $pola and $doge",
            "created_at": "Sat May 11 23:32:38 +0000 2024",
            "retweet": 1,
            "likes": 3,
            "retweeted_tweet": null
        },
        {
            "tweet_count": 24,
            "username": "Osagie💫",
            "user_account": "iosagie_X",
            "text": "@MonstersCoins Today buy Radical $DOGE on #Radix\n\nThis is why you should!\n1st- The security on the ecosystem  is second to none¡\n2nd- Radical $DOGE is still freaking early.\n3rd- There's bulk of room available in this pack for a healthy 100x and more!! 🚀🚀\n@Doge_Radix  @RadixGui https://t.co/opjQxENgfV",
            "created_at": "Sat May 11 23:32:38 +0000 2024",
            "retweet": 1,
            "likes": 7,
            "retweeted_tweet": null
        },
        {
            "tweet_count": 25,
            "username": "Luna 🏳️‍⚧️ ★",
            "user_account": "embiidsrevenge",
            "text": "@HoodiBones my metamask wallet has been hacked i need robux fortnite vbucks clash royale gems meta mask crypto doge coin",
            "created_at": "Sat May 11 23:31:33 +0000 2024",
            "retweet": 0,
            "likes": 2,
            "retweeted_tweet": null
        },
        {
            "tweet_count": 26,
            "username": "𝕏Ð",
            "user_account": "xdgood0420",
            "text": "@dogeofficialceo Dogecoin is money. @elonmusk",
            "created_at": "Sat May 11 23:29:21 +0000 2024",
            "retweet": 0,
            "likes": 0,
            "retweeted_tweet": null
        }
    ]
}