{
  "PEPE": [
    {
      "tweet_count": 1,
      "username": "Crypto-Trading📊",
      "text": "It's a day! Unbelievable ! Our new member achieved 1 1 4 0.57 % on $AIXBT ! Don’t miss out—start your FREE trial today for exclusive alerts and tips ! !  - https://t.co/2irlv0fhB4 - Be engaged! \n\n$BTC $XRP $USDC $PEPE $LINK $MNT $SUI $ETH $DOGE $SOL https://t.co/5GOChTrpMw",
      "created_at": "Wed Feb 05 13:18:56 +0000 2025",
      "retweet": 0,
      "likes": 0
    },
    {
      "tweet_count": 2,
      "username": "Crypto-Trading📊",
      "text": "It's Wondrous! Amazing win ! Our analyst made 1 2 1 0.06 % profit on $VIRTUAL ! Start your journey with a 14 -DAY FREE trial and receive exclusive market alerts ! !  - https://t.co/2irlv0fhB4 - Join us! \n\n$ETH $MNT $DOGE $USDC $PEPE $SOL $ADA $ONDO $SUI $BTC https://t.co/5JbuBt3pLc",
      "created_at": "Wed Feb 05 13:18:38 +0000 2025",
      "retweet": 0,
      "likes": 0
    },
    {
      "tweet_count": 3,
      "username": "Crypto-Trading📊",
      "text": "Yippee! Our junior analyst nailed 4 1 3 0.9 % profit on $GRIFFAIN ! Get started today with a 14 -DAY FREE trial and access expert ANALYST signals ! !  - https://t.co/2irlv0fhB4 - Be part now! \n\n$TRUMP $XRP $USDC $SOL $SUI $ETH $LINK $MNT $PEPE $BTC https://t.co/L1LnMfPVVv",
      "created_at": "Wed Feb 05 13:18:13 +0000 2025",
      "retweet": 0,
      "likes": 0
    },
    {
      "tweet_count": 4,
      "username": "Crypto-Trading📊",
      "text": "It's Stellar! A member just made an impressive 1 3 5 0.46 % profit on $TRUMP ! Ready to take your shot ? Join us now with a 14 -DAY FREE trial ! !  - https://t.co/2irlv0fhB4 - Make the move! \n\n$TRUMP $SUI $SOL $LINK $BTC $USDC $MNT $ONDO $PEPE $ETH https://t.co/DiPWPUnItx",
      "created_at": "Wed Feb 05 13:17:03 +0000 2025",
      "retweet": 0,
      "likes": 0
    },
    {
      "tweet_count": 5,
      "username": "Crypto-Trading📊",
      "text": "It's Glowing! Our newest member just crushed it with 2 8 0.49 % profit on $ETH ! Ready to start winning too ? Claim your 14 -DAY FREE trial now ! !  - https://t.co/2irlv0fhB4 - Make the move! \n\n$PEPE $MNT $USDC $SUI $ADA $LINK $DOGE $ETH $SOL $BTC https://t.co/hhyaIRUnnx",
      "created_at": "Wed Feb 05 13:16:45 +0000 2025",
      "retweet": 0,
      "likes": 0
    },
    {
      "tweet_count": 6,
      "username": "Crypto-Trading📊",
      "text": "Whoho! Our top trader just achieved 1 1 5 0.67 % on $KEKIUS ! Ready to profit big ? Join the 14 -DAY FREE trial now ! !  - https://t.co/2irlv0fhB4 - Join today! \n\n$MNT $ADA $SOL $BTC $DOGE $ETH $SUI $USDC $PEPE $XRP https://t.co/lFJUdXFmyN",
      "created_at": "Wed Feb 05 13:16:27 +0000 2025",
      "retweet": 0,
      "likes": 0
    },
    {
      "tweet_count": 7,
      "username": "Crypto-Trading📊",
      "text": "Zippy! A member just achieved 1 5 6 0.22 % profit on $BTC ! Start your 14 -DAY FREE trial today to get in on the action ! !  - https://t.co/2irlv0fhB4 - Just do it! \n\n$DOGE $SOL $XRP $ETH $LINK $USDC $PEPE $BTC $SUI $ADA https://t.co/mcwiMNH87P",
      "created_at": "Wed Feb 05 13:16:05 +0000 2025",
      "retweet": 0,
      "likes": 2
    },
    {
      "tweet_count": 8,
      "username": "Crypto-Trading📊",
      "text": "It's Buzzing! One of our members just earned an amazing 8 , 7 4 2 0.3 % return on $TRUMP ! Ready to achieve similar success ? Join us now and get a 14 -DAY FREE trial !  - https://t.co/2irlv0eJLw - Act now! \n\n$ETH $XRP $DOGE $SOL $ADA $LINK $SUI $USDC $PEPE $BTC https://t.co/7c0VNqGQ2N",
      "created_at": "Wed Feb 05 10:54:17 +0000 2025",
      "retweet": 0,
      "likes": 0
    },
    {
      "tweet_count": 9,
      "username": "Crypto-Trading📊",
      "text": "Yay! Yo , Shinobi just called $ILV and we’re up 53 % Wanna catch moves like this ? Join us now .  - https://t.co/2irlv0eJLw - Take action! \n\n$BTC $ETH $DOGE $MNT $XRP $ADA $USDC $PEPE $SOL $SUI https://t.co/p8UpKcAUlC",
      "created_at": "Wed Feb 05 10:53:50 +0000 2025",
      "retweet": 0,
      "likes": 0
    },
    {
      "tweet_count": 10,
      "username": "Crypto-Trading📊",
      "text": "Just another day! Our newest member bagged 1 3 8 0.6 % with $SPX ! Start your 14 -day FREE trial now and make your own wins ! !  - https://t.co/2irlv0eJLw - Don't wait!\n\n $USDC $PEPE $DOGE $BTC $MNT $ETH $TRUMP $XRP $SOL $SUI https://t.co/efegv8fQcK",
      "created_at": "Wed Feb 05 10:53:07 +0000 2025",
      "retweet": 0,
      "likes": 0
    },
    {
      "tweet_count": 11,
      "username": "Crypto-Trading📊",
      "text": "It's a Bliss! Incredible wins ! 3 , 9 4 0.69 % on $TRUMPOFFICIAL ! Want to see similar results ? Jump in with a 14 day FREE Trial!  - https://t.co/2irlv0eJLw - Be part now!\n\n $MNT $LINK $USDC $SUI $ETH $ADA $DOGE $PEPE $SOL $BTC https://t.co/toaVbVzrDL",
      "created_at": "Wed Feb 05 10:52:50 +0000 2025",
      "retweet": 0,
      "likes": 0
    },
    {
      "tweet_count": 12,
      "username": "Crypto-Trading📊",
      "text": "It's Triumphant! One member soared 1 3 7 0.21 % on $ZEREBRO ! Don’t miss out— Start your 14 -day FREE trial and unlock your potential today ! !  - https://t.co/2irlv0eJLw - Sign today! \n\n$ADA $DOGE $USDC $PEPE $XRP $ETH $MNT $SUI $SOL $BTC https://t.co/N8q7gTh1qK",
      "created_at": "Wed Feb 05 10:52:29 +0000 2025",
      "retweet": 0,
      "likes": 0
    },
    {
      "tweet_count": 13,
      "username": "Crypto-Trading📊",
      "text": "I'm Uplifted! Join us now for $38 only : Insane gains ! ( Your link ) Our analyst just pulled a Massive 230 % profits on $NEIROETH . Want in ? Hit up a 14 day FREE Trial!  - https://t.co/2irlv0eJLw - Let's go! \n\n$SUI $SOL $USDC $MNT $ADA $PEPE $ETH $TRUMP $XRP $BTC https://t.co/Jgdur14dup",
      "created_at": "Wed Feb 05 10:51:55 +0000 2025",
      "retweet": 0,
      "likes": 0
    },
    {
      "tweet_count": 14,
      "username": "Crypto-Trading📊",
      "text": "Yippee! A member just bagged 5 .94 % on $ETH ! Ready for success ? Start your 14 -day FREE trial and get expert alerts today ! !  - https://t.co/2irlv0eJLw - Now or never! \n\n$TRUMP $PEPE $ETH $XRP $SOL $DOGE $USDC $ADA $LINK $BTC https://t.co/zmoXnEHqKp",
      "created_at": "Wed Feb 05 10:50:55 +0000 2025",
      "retweet": 0,
      "likes": 0
    },
    {
      "tweet_count": 15,
      "username": "Crypto-Trading📊",
      "text": "Just Rolling! WOW ! A new member just gained 4 5 8 0.27 % on $MOODENG ! Don’t wait—join our 14 -day FREE trial now and get instant access to expert alerts ! !  - https://t.co/2irlv0eJLw - Sign on! \n\n$TRUMP $XRP $PEPE $SUI $ETH $LINK $SOL $USDC $MNT $BTC https://t.co/pQNgehvKMj",
      "created_at": "Wed Feb 05 10:50:39 +0000 2025",
      "retweet": 0,
      "likes": 0
    },
    {
      "tweet_count": 16,
      "username": "Crypto-Trading📊",
      "text": "High-five! Our member earned 5 5 6 0.59 % profit with $KAS ! Ready for big gains ? Sign up for a FREE 14 -DAY trial today ! !  - https://t.co/2irlv0eJLw - Hurry in! \n\n$ADA $DOGE $BTC $SUI $ONDO $ETH $USDC $SOL $PEPE $TRUMP https://t.co/zhWA1E1TLq",
      "created_at": "Wed Feb 05 10:50:20 +0000 2025",
      "retweet": 0,
      "likes": 0
    },
    {
      "tweet_count": 17,
      "username": "Crypto-Trading📊",
      "text": "It's Stellar! One of our members made an impressive 4 2 0.86 % return on $SOL ! Don’t wait – get your FREE 14 -DAY trial and start trading like a pro ! !  -  https://t.co/2irlv0eJLw Stay with us! \n\n$ETH $BTC $LINK $PEPE $USDC $SUI $ADA $SOL $TRUMP $MNT https://t.co/qf00OYBaw8",
      "created_at": "Wed Feb 05 10:50:02 +0000 2025",
      "retweet": 0,
      "likes": 0
    },
    {
      "tweet_count": 18,
      "username": "Crypto-Trading📊",
      "text": "It's a Delight! A member just hit 1 2 5 0.98 % on $GOAT ! Want to achieve the same ? Start your 14 -day FREE trial and get pro -level trading alerts !  - https://t.co/2irlv0eJLw - Come join us! \n\n$ETH $TRUMP $ADA $BTC $PEPE $MNT $LINK $SUI $SOL $USDC https://t.co/9xpMrYAISv",
      "created_at": "Wed Feb 05 10:49:38 +0000 2025",
      "retweet": 0,
      "likes": 0
    },
    {
      "tweet_count": 19,
      "username": "Crypto-Trading📊",
      "text": "Neat! Incredible wins ! 3 , 9 4 0.69 % on $TRUMPOFFICIAL ! Want to see similar results ? Jump in with a 14 day FREE Trial!  - https://t.co/2irlv0eJLw - Come in! \n\n$MNT $TRUMP $SOL $ONDO $ETH $PEPE $LINK $SUI $USDC $BTC https://t.co/vSjowEt7hv",
      "created_at": "Wed Feb 05 08:59:31 +0000 2025",
      "retweet": 0,
      "likes": 0
    },
    {
      "tweet_count": 20,
      "username": "Crypto-Trading📊",
      "text": "Booyah! One of our member made a massive 5 5 0 0.98 % profit with $JELLYJELLY ! Want to see similar results ? Start your 14 -DAY FREE trial ! !  - https://t.co/2irlv0eJLw - You got this!\n\n $DOGE $BTC $XRP $PEPE $ONDO $ETH $ADA $USDC $MNT $SOL https://t.co/AmAeZCEsPP",
      "created_at": "Wed Feb 05 08:59:09 +0000 2025",
      "retweet": 0,
      "likes": 0
    },
    {
      "tweet_count": 21,
      "username": "Crypto-Trading📊",
      "text": "It's Splendid! Just caught the bottom and bounced out at the top . Locked in a solid 109 % gain on $SOL !  - https://t.co/2irlv0eJLw - Just do it! \n\n$ONDO $MNT $TRUMP $ADA $SOL $LINK $USDC $ETH $PEPE $BTC https://t.co/ajTdV4tUjO",
      "created_at": "Wed Feb 05 08:58:27 +0000 2025",
      "retweet": 0,
      "likes": 0
    },
    {
      "tweet_count": 22,
      "username": "Crypto-Trading📊",
      "text": "It's Exciting! Our member just made a 1 , 6 3 4 0.71 % profit on $ETH ! Don’t miss your chance—grab your 14 -DAY FREE trial now ! !  - https://t.co/2irlv0eJLw - Join quickly!\n\n $BTC $PEPE $DOGE $ONDO $SOL $USDC $SUI $XRP $ADA $ETH https://t.co/DRCH6gX3KW",
      "created_at": "Wed Feb 05 08:57:54 +0000 2025",
      "retweet": 0,
      "likes": 0
    },
    {
      "tweet_count": 23,
      "username": "Crypto-Trading📊",
      "text": "It's Amazing! Primal nailed it—called $HBAR and we’re up 160 % ! Wanna get in on the next big move ? Join us now Try it FREE for 14 days . Don’t miss your shot !  - https://t.co/2irlv0eJLw - Step in! \n\n$MNT $ADA $ETH $ONDO $PEPE $SUI $SOL $USDC $DOGE $BTC https://t.co/qB9xE8rZL2",
      "created_at": "Wed Feb 05 08:57:35 +0000 2025",
      "retweet": 0,
      "likes": 0
    },
    {
      "tweet_count": 24,
      "username": "Crypto-Trading📊",
      "text": "It's a day! Our member made an incredible 1 5 7 0.67 % profit on $AAVE ! Ready to level up ? Start your FREE 14 -day trial now ! !  - https://t.co/2irlv0eJLw - Join right in!\n\n $USDC $ETH $PEPE $XRP $DOGE $SOL $LINK $MNT $ADA $BTC https://t.co/fEdxI9apNy",
      "created_at": "Wed Feb 05 08:57:15 +0000 2025",
      "retweet": 0,
      "likes": 0
    },
    {
      "tweet_count": 25,
      "username": "Crypto-Trading📊",
      "text": "It's Splendid! Our junior analyst just saw 2 7 9 0.55 % on $BTC ! Want results like this ? Start your 14 -DAY FREE trial today ! !  - https://t.co/2irlv0eJLw - Be included! \n\n$DOGE $XRP $PEPE $ADA $SOL $ONDO $MNT $USDC $BTC $ETH https://t.co/g7TSkdiTqE",
      "created_at": "Wed Feb 05 08:56:55 +0000 2025",
      "retweet": 0,
      "likes": 0
    },
    {
      "tweet_count": 26,
      "username": "Crypto-Trading📊",
      "text": "Boom! Our member just locked in a 2 3 0.75 % return on $VINE ! Ready to join ? Start your FREE 14 -day trial today ! !  - https://t.co/2irlv0eJLw - Try it out!\n\n $PEPE $ETH $SOL $BTC $TRUMP $USDC $MNT $XRP $DOGE $ADA https://t.co/m1fEP2sfIN",
      "created_at": "Wed Feb 05 08:56:37 +0000 2025",
      "retweet": 0,
      "likes": 1
    },
    {
      "tweet_count": 27,
      "username": "Crypto-Trading📊",
      "text": "Booyah! Just locked in a juicy 60 % on $HYPE Don’t sleep—this is your cue to hop in the Discord .  - https://t.co/2irlv0eJLw - You can do! \n\n$BTC $XRP $DOGE $ETH $PEPE $ADA $MNT $USDC $SUI $SOL https://t.co/Q1LAAhdDve",
      "created_at": "Wed Feb 05 08:46:40 +0000 2025",
      "retweet": 0,
      "likes": 0
    },
    {
      "tweet_count": 28,
      "username": "Crypto-Trading📊",
      "text": "Blazing! Massive Win ! Another member achieved 5 1 2 0.18 % on $1000PEPE ! Ready to make big moves ? Claim your 14 -day FREE trial now !  - https://t.co/2irlv0eJLw - Join free! \n\n$TRUMP $ETH $SUI $BTC $USDC $SOL $PEPE $ONDO $DOGE $LINK https://t.co/D9nTzPMz10",
      "created_at": "Wed Feb 05 08:45:37 +0000 2025",
      "retweet": 0,
      "likes": 0
    },
    {
      "tweet_count": 29,
      "username": "Crypto-Trading📊",
      "text": "Broh! Our top trader just secured 1 2 4 0.59 % profit on $FARTCOIN ! Don’t miss out—start your 14 -DAY FREE trial now and trade like a pro ! !  - https://t.co/2irlv0eJLw - Try it today! \n\n$ADA $TRUMP $USDC $DOGE $SOL $XRP $SUI $BTC $PEPE $ETH https://t.co/NdfwRBRIsw",
      "created_at": "Wed Feb 05 08:44:56 +0000 2025",
      "retweet": 0,
      "likes": 0
    },
    {
      "tweet_count": 30,
      "username": "Crypto-Trading📊",
      "text": "Kudos! A member just made an impressive 1 3 5 0.46 % profit on $TRUMP ! Ready to take your shot ? Join us now with a 14 -DAY FREE trial ! !  - https://t.co/2irlv0eJLw - Don't miss! \n\n$XRP $TRUMP $PEPE $ETH $DOGE $USDC $BTC $ADA $LINK $SOL https://t.co/99YMXmr0h4",
      "created_at": "Wed Feb 05 08:44:29 +0000 2025",
      "retweet": 0,
      "likes": 0
    },
    {
      "tweet_count": 31,
      "username": "Crypto-Trading📊",
      "text": "Hippy! Jodez , our senior analyst , just achieved an incredible 1 , 3 8 2 0.1 % profit on $TRUMP ! Want similar results ? Start your 14 day FREE Trial!  - https://t.co/2irlv0eJLw - Go join us! \n\n$PEPE $USDC $TRUMP $XRP $ETH $SOL $ONDO $LINK $MNT $BTC https://t.co/ZsO9hNfxB6",
      "created_at": "Wed Feb 05 08:44:07 +0000 2025",
      "retweet": 0,
      "likes": 0
    },
    {
      "tweet_count": 32,
      "username": "Crypto-Trading📊",
      "text": "Great! Our newest member just crushed it with 2 8 0.49 % profit on $ETH ! Ready to start winning too ? Claim your 14 -DAY FREE trial now ! !  - https://t.co/2irlv0eJLw - Claim your spot!\n\n $XRP $TRUMP $DOGE $PEPE $BTC $LINK $USDC $ETH $SOL $ADA https://t.co/TFozYh3hSd",
      "created_at": "Wed Feb 05 08:43:50 +0000 2025",
      "retweet": 0,
      "likes": 0
    },
    {
      "tweet_count": 33,
      "username": "Crypto-Trading📊",
      "text": "Booyah! One of our member made a massive 5 5 0 0.98 % profit with $JELLYJELLY ! Want to see similar results ? Start your 14 -DAY FREE trial ! !  - https://t.co/2irlv0eJLw - You got this! \n\n$DOGE $BTC $XRP $PEPE $ONDO $ETH $ADA $USDC $MNT $SOL https://t.co/4AauOVSbQ3",
      "created_at": "Wed Feb 05 08:43:24 +0000 2025",
      "retweet": 0,
      "likes": 0
    },
    {
      "tweet_count": 34,
      "username": "Crypto-Trading📊",
      "text": "Woohoo! Primal nailed it—called $HBAR and we’re up 160 % ! Wanna get in on the next big move ? Join us now Try it FREE for 14 days . Don’t miss your shot !  - https://t.co/2irlv0eJLw - Join for free! \n\n$BTC $MNT $USDC $SUI $SOL $ONDO $ETH $LTC $PEPE $TRUMP https://t.co/a7SB80ldQv",
      "created_at": "Wed Feb 05 02:32:25 +0000 2025",
      "retweet": 0,
      "likes": 0
    },
    {
      "tweet_count": 35,
      "username": "Crypto-Trading📊",
      "text": "Yippee! Check this out ! Our newest member made 1 0 2 0.66 % GAINS on $SOL with expert signals from our team ! Want to see results ? Start your 14 -Day Free Trial today !  - https://t.co/2irlv0eJLw - Join us! \n\n$ETH $SOL $DOGE $XRP $SUI $BTC $PEPE $LINK $ONDO $USDC https://t.co/uCasFWFZ0R",
      "created_at": "Wed Feb 05 02:31:38 +0000 2025",
      "retweet": 0,
      "likes": 1
    },
    {
      "tweet_count": 36,
      "username": "Crypto-Trading📊",
      "text": "Hurrayy! Our member just hit 2 9 5 0.58 % profit on $ETH ! Get started with a 14 -DAY FREE trial and see how you can achieve these gains ! !  - https://t.co/2irlv0eJLw - Claim today! \n\n$LTC $BTC $USDC $TRUMP $MNT $LINK $ETH $SOL $SUI $PEPE https://t.co/0E3iYNP1GA",
      "created_at": "Wed Feb 05 02:31:27 +0000 2025",
      "retweet": 0,
      "likes": 1
    },
    {
      "tweet_count": 37,
      "username": "Crypto-Trading📊",
      "text": "It's a Jollyday! Unbelievable ! Our new member achieved 1 1 4 0.57 % on $AIXBT ! Don’t miss out—start your FREE trial today for exclusive alerts and tips ! !  - https://t.co/2irlv0eJLw - Join for alerts! \n\n$DOGE $ETH $ONDO $USDC $SUI $ADA $PEPE $SOL $MNT $BTC https://t.co/N8fW6nbESv",
      "created_at": "Wed Feb 05 02:30:47 +0000 2025",
      "retweet": 0,
      "likes": 0
    },
    {
      "tweet_count": 38,
      "username": "Crypto-Trading📊",
      "text": "It's Wondrous! Amazing win ! Our analyst made 1 2 1 0.06 % profit on $VIRTUAL ! Start your journey with a 14 -DAY FREE trial and receive exclusive market alerts ! !  - https://t.co/2irlv0eJLw - Come aboard!\n\n $SOL $ETH $LINK $PEPE $SUI $TRUMP $DOGE $ONDO $BTC $USDC https://t.co/HqhC6fVr4v",
      "created_at": "Wed Feb 05 02:30:28 +0000 2025",
      "retweet": 0,
      "likes": 0
    },
    {
      "tweet_count": 39,
      "username": "Crypto-Trading📊",
      "text": "It's Shining! Our analysts just smashed it with a 87 % gain shorting $COOKIE ! You tryna secure the bag too ? Grab your FREE 14 -day trial now !  - https://t.co/2irlv0eJLw - Get it now! \n\n$BTC $MNT $ONDO $TRUMP $ETH $DOGE $SOL $XRP $USDC $PEPE https://t.co/UdAO9TlLFg",
      "created_at": "Wed Feb 05 02:30:24 +0000 2025",
      "retweet": 0,
      "likes": 0
    },
    {
      "tweet_count": 40,
      "username": "Crypto-Trading📊",
      "text": "Cheers! A member just made an impressive 1 3 5 0.46 % profit on $TRUMP ! Ready to take your shot ? Join us now with a 14 -DAY FREE trial ! !  - https://t.co/2irlv0eJLw - Don't wait!\n\n $SOL $LTC $PEPE $SUI $ETH $USDC $ONDO $TRUMP $BTC $LINK https://t.co/SDNN5t8APS",
      "created_at": "Wed Feb 05 02:21:19 +0000 2025",
      "retweet": 0,
      "likes": 0
    },
    {
      "tweet_count": 41,
      "username": "Crypto-Trading📊",
      "text": "I'm Elated! One of our members made an impressive 4 2 0.86 % return on $SOL ! Don’t wait – get your FREE 14 -DAY trial and start trading like a pro ! !  - https://t.co/2irlv0eJLw - Don't delay!\n\n $XRP $MNT $BTC $ETH $SOL $ONDO $SUI $DOGE $PEPE $USDC https://t.co/HwO1S5avcI",
      "created_at": "Wed Feb 05 02:20:54 +0000 2025",
      "retweet": 0,
      "likes": 0
    },
    {
      "tweet_count": 42,
      "username": "Crypto-Trading📊",
      "text": "It's Exciting! One of our members just earned an amazing 8 , 7 4 2 0.3 % return on $TRUMP ! Ready to achieve similar success ? Join us now and get a 14 -DAY FREE trial !  - https://t.co/2irlv0eJLw - Join quickly! \n\n$ONDO $DOGE $TRUMP $USDC $PEPE $ENA $SOL $BTC $ETH $LTC https://t.co/ExPB42MoTK",
      "created_at": "Wed Feb 05 02:19:13 +0000 2025",
      "retweet": 0,
      "likes": 0
    },
    {
      "tweet_count": 43,
      "username": "Crypto-Trading📊",
      "text": "Magnificent! Our new member just banked 1 3 2 0.55 % in gains on $ETH after using our expert signals ! Don’t wait — Sign up for your 14 -Day FREE trial today ! !  - https://t.co/2irlv0fhB4 - Act quickly! \n\n$TRUMP $PEPE $USDC $LINK $ETH $SOL $SUI $ADA $ONDO $BTC https://t.co/ZN1ZKFicp5",
      "created_at": "Wed Feb 05 02:18:15 +0000 2025",
      "retweet": 0,
      "likes": 0
    },
    {
      "tweet_count": 44,
      "username": "Crypto-Trading📊",
      "text": "Woohoo! Primal nailed it—called $HBAR and we’re up 160 % ! Wanna get in on the next big move ? Join us now Try it FREE for 14 days . Don’t miss your shot !  - https://t.co/2irlv0eJLw - Join for free!\n\n $BTC $MNT $USDC $SUI $SOL $ONDO $ETH $LTC $PEPE $TRUMP https://t.co/EkX3Iv3G47",
      "created_at": "Wed Feb 05 02:17:36 +0000 2025",
      "retweet": 0,
      "likes": 0
    },
    {
      "tweet_count": 45,
      "username": "Crypto-Trading📊",
      "text": "It's Zinging! Our junior analyst just saw 2 7 9 0.55 % on $BTC ! Want results like this ? Start your 14 -DAY FREE trial today ! !  - https://t.co/2irlv0fhB4 - Get started! \n\n$MNT $LTC $SUI $ONDO $SOL $TRUMP $USDC $PEPE $BTC $ETH https://t.co/hrwzMrkCwL",
      "created_at": "Sat Feb 08 15:30:56 +0000 2025",
      "retweet": 0,
      "likes": 1
    },
    {
      "tweet_count": 46,
      "username": "Crypto-Trading📊",
      "text": "Bravo! Our member earned 5 5 6 0.59 % profit with $KAS ! Ready for big gains ? Sign up for a FREE 14 -DAY trial today ! !  - https://t.co/2irlv0fhB4 - Act with us! \n\n$ONDO $XRP $LTC $MNT $PEPE $USDC $ETH $BTC $SOL $TRUMP https://t.co/wVQVtlXub2",
      "created_at": "Sat Feb 08 15:28:36 +0000 2025",
      "retweet": 0,
      "likes": 3
    },
    {
      "tweet_count": 47,
      "username": "Crypto-Trading📊",
      "text": "All right! Amazing return ! Our new member turned 2 5 3 0.39 % profit on $ETH ! Don t miss out – start your FREE 14 -DAY trial today and get insider market tips !  - https://t.co/2irlv0fhB4 - Try it out!\n\n $PEPE $DOGE $SOL $SUI $ETH $BTC $ONDO $USDC $ADA $TRUMP https://t.co/ROjU4mxfEz",
      "created_at": "Sat Feb 08 15:27:12 +0000 2025",
      "retweet": 0,
      "likes": 1
    },
    {
      "tweet_count": 48,
      "username": "Crypto-Trading📊",
      "text": "Zippy! One member gained 6 7 5 0.8 % on $LIQD ! Join now—start your 14 -day FREE trial and make your next move ! !  - https://t.co/2irlv0fhB4 - Join us! \n\n$BTC $ADA $PEPE $TRUMP $XRP $LTC $USDC $SOL $ETH $MNT https://t.co/AN9yGXBzJj",
      "created_at": "Sat Feb 08 15:24:57 +0000 2025",
      "retweet": 0,
      "likes": 3
    },
    {
      "tweet_count": 49,
      "username": "Crypto-Trading📊",
      "text": "Rock'n on! Yo , massive W secured ! Just ran up a 253 % gain on $DOGE—big ups to the team and the brainiacs who called it . Let’s keep the grind strong !  - https://t.co/2irlv0eJLw - Come join us! \n\n$DOGE $TRUMP $LTC $MNT $BTC $ONDO $ETH $PEPE $USDC $SOL https://t.co/8ksQ8YkOul",
      "created_at": "Sat Feb 08 15:23:51 +0000 2025",
      "retweet": 0,
      "likes": 3
    },
    {
      "tweet_count": 50,
      "username": "Crypto-Trading📊",
      "text": "It's Super! A member just achieved 1 6 4 0.9 % on $XCN ! Get started with your 14 -DAY FREE trial and start making smarter trades ! !  - https://t.co/2irlv0fhB4 - Sign today! \n\n$DOGE $ETH $USDC $SOL $PEPE $ADA $XRP $MNT $ONDO $BTC https://t.co/kj03B192Qm",
      "created_at": "Sat Feb 08 14:12:32 +0000 2025",
      "retweet": 0,
      "likes": 1
    },
    {
      "tweet_count": 51,
      "username": "Crypto-Trading📊",
      "text": "It's Glorious! Massive win from our junior analyst with 1 2 4 5 0.74 % profit on $FARTCOIN ! Ready to join the winning team ? Start your 14 -DAY FREE trial now !  - https://t.co/2irlv0fhB4 - Try now! \n\n$XRP $BTC $TRUMP $PEPE $ETH $MNT $USDC $LTC $ADA $SOL https://t.co/avNNy8t2N1",
      "created_at": "Sat Feb 08 14:12:05 +0000 2025",
      "retweet": 0,
      "likes": 0
    },
    {
      "tweet_count": 52,
      "username": "Crypto-Trading📊",
      "text": "It's Super! Just locked in a juicy 60 % on $HYPE Don’t sleep—this is your cue to hop in the Discord .  - https://t.co/2irlv0fhB4 - Be a member! \n\n$ETH $ADA $USDC $TRUMP $MNT $ONDO $SUI $SOL $PEPE $BTC https://t.co/HGlSO9dzQA",
      "created_at": "Sat Feb 08 14:11:24 +0000 2025",
      "retweet": 0,
      "likes": 0
    },
    {
      "tweet_count": 53,
      "username": "Crypto-Trading📊",
      "text": "I'm Over the moon! Just caught the bottom and bounced out at the top . Locked in a solid 109 % gain on $SOL !  - https://t.co/2irlv0fhB4 - Get in now! \n\n$PEPE $ADA $ETH $USDC $SOL $XRP $BTC $MNT $TRUMP $ONDO https://t.co/LCGUNniniI",
      "created_at": "Sat Feb 08 14:10:09 +0000 2025",
      "retweet": 0,
      "likes": 0
    },
    {
      "tweet_count": 54,
      "username": "Crypto-Trading📊",
      "text": "It's Zinging! Our junior analyst just saw 2 7 9 0.55 % on $BTC ! Want results like this ? Start your 14 -DAY FREE trial today ! !  - https://t.co/2irlv0fhB4 - Get started! \n\n$MNT $LTC $SUI $ONDO $SOL $TRUMP $USDC $PEPE $BTC $ETH https://t.co/Rkw1JRs9hE",
      "created_at": "Sat Feb 08 14:08:52 +0000 2025",
      "retweet": 0,
      "likes": 0
    },
    {
      "tweet_count": 55,
      "username": "Crypto-Trading📊",
      "text": "It's Splendid! Our newest member just crushed it with 2 8 0.49 % profit on $ETH ! Ready to start winning too ? Claim your 14 -DAY FREE trial now ! !  - https://t.co/2irlv0fhB4 - Get started!\n\n $LTC $XRP $DOGE $ETH $MNT $ONDO $USDC $BTC $SOL $PEPE https://t.co/fuu6scHaPT",
      "created_at": "Sat Feb 08 13:41:37 +0000 2025",
      "retweet": 0,
      "likes": 0
    },
    {
      "tweet_count": 56,
      "username": "Crypto-Trading📊",
      "text": "It's Super! Our top trader just secured 1 2 4 0.59 % profit on $FARTCOIN ! Don’t miss out—start your 14 -DAY FREE trial now and trade like a pro ! !  - https://t.co/2irlv0fhB4 - Come join us!\n\n $XRP $ETH $DOGE $USDC $MNT $SUI $ADA $SOL $BTC $PEPE https://t.co/UxqeBQk6Ne",
      "created_at": "Sat Feb 08 13:40:52 +0000 2025",
      "retweet": 0,
      "likes": 0
    },
    {
      "tweet_count": 57,
      "username": "Crypto-Trading📊",
      "text": "It's Fab! Big gains today ! Our new member made a 7 9 8 0.93 % profit on $AAVE ! Join us and start your 14 -DAY FREE trial today !  - https://t.co/2irlv0fhB4 - Stay with us! \n\n$XRP $MNT $PEPE $LTC $TRUMP $ETH $USDC $SOL $DOGE $BTC https://t.co/KbnEGK7QqL",
      "created_at": "Sat Feb 08 13:40:08 +0000 2025",
      "retweet": 0,
      "likes": 0
    },
    {
      "tweet_count": 58,
      "username": "Crypto-Trading📊",
      "text": "It's Glorious! Our member  made an incredible 5 8 .9 % profit on $HYPE ! Ready to join the success ? Start your 14 -DAY FREE trial today ! !  - https://t.co/2irlv0fhB4 - Grab one! \n\n$MNT $BTC $USDC $SOL $ETH $DOGE $ADA $XRP $PEPE $ONDO https://t.co/f2Eta9jT9B",
      "created_at": "Sat Feb 08 13:39:29 +0000 2025",
      "retweet": 0,
      "likes": 1
    },
    {
      "tweet_count": 59,
      "username": "Crypto-Trading📊",
      "text": "Woohoo! Our member just achieved a 9 2 .05 % profit on $ETH ! Don’t miss out—start your 14 -DAY FREE trial now ! !  - https://t.co/2irlv0fhB4 - Grab it now! \n\n$PEPE $DOGE $MNT $ETH $BTC $TRUMP $USDC $SUI $SOL $ONDO https://t.co/OnFRdA314J",
      "created_at": "Sat Feb 08 13:39:06 +0000 2025",
      "retweet": 0,
      "likes": 0
    },
    {
      "tweet_count": 60,
      "username": "Crypto-Trading📊",
      "text": "It's a Dream! Insane move on $VANA today ! 1 6 1 0.41 % gain , thanks to our expert ! Ready to level up ? Start your 14 day FREE Trial!  - https://t.co/2irlv0fhB4 - Don't miss! \n\n$ONDO $PEPE $ADA $SOL $XRP $ETH $BTC $MNT $LTC $USDC https://t.co/HEAaAfoudN",
      "created_at": "Sat Feb 08 13:38:37 +0000 2025",
      "retweet": 0,
      "likes": 0
    },
    {
      "tweet_count": 61,
      "username": "Crypto-Trading📊",
      "text": "Kudos! Our member just earned an incredible 2 6 0.41 % profit on $MDOGS ! Want in ? Start your 14 -DAY FREE trial now ! !  - https://t.co/2irlv0fhB4 - Grab one!\n\n $SOL $USDC $SUI $DOGE $ETH $LTC $TRUMP $ONDO $BTC $PEPE https://t.co/uojnSozQAm",
      "created_at": "Sat Feb 08 13:37:57 +0000 2025",
      "retweet": 0,
      "likes": 0
    },
    {
      "tweet_count": 62,
      "username": "Crypto-Trading📊",
      "text": "Hippy! One of our members made a massive 1 2 0.8 % profit with $VINE ! Want in on the next big win ? Start your 14 -DAY FREE trial now ! !  - https://t.co/2irlv0fhB4 - Make the move!\n\n$BTC $TRUMP $USDC $ADA $PEPE $SOL $ETH $DOGE $ONDO $MNT https://t.co/zXIE6PWQiT",
      "created_at": "Sat Feb 08 13:37:38 +0000 2025",
      "retweet": 0,
      "likes": 0
    },
    {
      "tweet_count": 63,
      "username": "Crypto-Trading📊",
      "text": "It's Fantastic! Another member made 283 % profit on $VINE ! Sign up today for a 14 -DAY FREE trial and start receiving expert trade tips ! !  - https://t.co/2irlv0fhB4 - Don't hesitate! \n\n$MNT $SUI $ETH $USDC $BTC $XRP $ADA $SOL $TRUMP $PEPE https://t.co/63IoAoo0vK",
      "created_at": "Sat Feb 08 13:25:56 +0000 2025",
      "retweet": 0,
      "likes": 1
    },
    {
      "tweet_count": 64,
      "username": "Crypto-Trading📊",
      "text": "It's Glorious! Massive win from our junior analyst with 1 2 4 5 0.74 % profit on $FARTCOIN ! Ready to join the winning team ? Start your 14 -DAY FREE trial now !  - https://t.co/2irlv0fhB4 - Try now!\n\n $XRP $BTC $TRUMP $PEPE $ETH $MNT $USDC $LTC $ADA $SOL https://t.co/3XxxXf65Bj",
      "created_at": "Sat Feb 08 13:25:05 +0000 2025",
      "retweet": 0,
      "likes": 0
    },
    {
      "tweet_count": 65,
      "username": "Crypto-Trading📊",
      "text": "It's Upbeat! A member just achieved 1 5 6 0.22 % profit on $BTC ! Start your 14 -DAY FREE trial today to get in on the action ! !  - https://t.co/2irlv0fhB4 - Don't miss!\n\n $ONDO $TRUMP $SOL $PEPE $BTC $DOGE $ETH $ADA $USDC $XRP https://t.co/9jXOJZxisG",
      "created_at": "Sat Feb 08 05:24:22 +0000 2025",
      "retweet": 0,
      "likes": 0
    },
    {
      "tweet_count": 66,
      "username": "Crypto-Trading📊",
      "text": "Magnificent! Massive win from our junior analyst with 1 2 4 5 0.74 % profit on $FARTCOIN ! Ready to join the winning team ? Start your 14 -DAY FREE trial now !  - https://t.co/2irlv0fhB4 - Don't hesitate!\n\n $ADA $ONDO $DOGE $PEPE $ETH $USDC $TRUMP $SUI $BTC $SOL https://t.co/RT8dh1qqzo",
      "created_at": "Sat Feb 08 05:23:04 +0000 2025",
      "retweet": 0,
      "likes": 2
    },
    {
      "tweet_count": 67,
      "username": "Crypto-Trading📊",
      "text": "It's Upbeat! Our member just achieved 2 7 1 0.44 % profit on $PUMPAI ! Don’t wait—claim your 14 -DAY FREE trial today ! !  - https://t.co/2irlv0fhB4 - Join today! \n\n$ETH $USDC $SOL $MNT $SUI $ONDO $PEPE $XRP $TRUMP $BTC https://t.co/fTEQsS3ZJJ",
      "created_at": "Sat Feb 08 05:22:20 +0000 2025",
      "retweet": 0,
      "likes": 0
    },
    {
      "tweet_count": 68,
      "username": "Crypto-Trading📊",
      "text": "Just Rolling! One of our members just made 2 4 6 0.56 % profit on $MELANIA ! Want in on the action ? Start your 14 -DAY FREE trial today ! !  - https://t.co/2irlv0fhB4 - Act fast! \n\n$USDC $TRUMP $BTC $ETH $MNT $ONDO $SUI $PEPE $LTC $SOL https://t.co/XqclpF0B5J",
      "created_at": "Sat Feb 08 05:22:04 +0000 2025",
      "retweet": 0,
      "likes": 0
    },
    {
      "tweet_count": 69,
      "username": "Crypto-Trading📊",
      "text": "It's a Bliss! A member just achieved 1 5 6 0.22 % profit on $BTC ! Start your 14 -DAY FREE trial today to get in on the action ! !  - https://t.co/2irlv0fhB4 - Join it now!\n\n $ETH $DOGE $SOL $ONDO $USDC $XRP $PEPE $MNT $BTC $TRUMP https://t.co/DyxYLfj6kM",
      "created_at": "Sat Feb 08 05:21:23 +0000 2025",
      "retweet": 0,
      "likes": 1
    },
    {
      "tweet_count": 70,
      "username": "Crypto-Trading📊",
      "text": "It's Zinging! One of our members just made an incredible 1 , 3 9 7 0.65 % profit on $MELANIA ! Want to join the success ? Start your 14 -DAY FREE trial now !  - https://t.co/2irlv0fhB4 - Just do it! \n\n$BTC $SOL $ONDO $ETH $ADA $PEPE $USDC $TRUMP $LTC $MNT https://t.co/aICSI3Cjlt",
      "created_at": "Sat Feb 08 05:21:02 +0000 2025",
      "retweet": 0,
      "likes": 0
    },
    {
      "tweet_count": 71,
      "username": "Crypto-Trading📊",
      "text": "Hooray! Our member just locked in a 2 3 0.75 % return on $VINE ! Ready to join ? Start your FREE 14 -day trial today ! !  - https://t.co/2irlv0fhB4 - Be involved!\n\n $PEPE $TRUMP $LINK $MNT $BTC $SOL $USDC $SUI $DOGE $ETH https://t.co/yTBaUypss4",
      "created_at": "Sat Feb 08 05:19:40 +0000 2025",
      "retweet": 0,
      "likes": 0
    },
    {
      "tweet_count": 72,
      "username": "Crypto-Trading📊",
      "text": "It's a day! Primal , our top trader , just nailed a 8 0.19 % profit on $HOLD ! Ready to join the winning team ? Start your 14 -DAY FREE trial today  - https://t.co/2irlv0fhB4 - Don't delay!\n\n $ONDO $XRP $TRUMP $ADA $DOGE $USDC $ETH $SOL $BTC $PEPE https://t.co/faHbO02skE",
      "created_at": "Sat Feb 08 05:19:28 +0000 2025",
      "retweet": 0,
      "likes": 1
    },
    {
      "tweet_count": 73,
      "username": "Crypto-Trading📊",
      "text": "Viva! A member just made 1 6 0.26 % profit from $BUTTHOLE ! Want in ? Get your 14 -day FREE trial today ! !  - https://t.co/2irlv0fhB4 - Try it out!\n\n $USDC $LINK $PEPE $XRP $ETH $SOL $SUI $MNT $DOGE $BTC https://t.co/JCbASOFHuc",
      "created_at": "Sat Feb 08 05:19:03 +0000 2025",
      "retweet": 0,
      "likes": 1
    },
    {
      "tweet_count": 74,
      "username": "Crypto-Trading📊",
      "text": "I'm Energized! Our member  made an incredible 5 8 .9 % profit on $HYPE ! Ready to join the success ? Start your 14 -DAY FREE trial today ! !  - https://t.co/2irlv0eJLw - Get started! \n\n$SOL $BTC $LINK $ETH $PEPE $TRUMP $USDC $SUI $XRP $MNT https://t.co/5WUPrKEMFc",
      "created_at": "Sat Feb 08 05:18:00 +0000 2025",
      "retweet": 0,
      "likes": 0
    },
    {
      "tweet_count": 75,
      "username": "Crypto-Trading📊",
      "text": "It's Awesome! One of our member just locked in a 1 0 0.15 % profit on $ORDI ! Want to make gains like this ? Join now with a 14 -DAY FREE trial ! !  - https://t.co/2irlv0eJLw - Stay with us! \n\n$PEPE $BTC $SOL $LINK $USDC $MNT $SUI $TRUMP $ETH $XRP https://t.co/s6t5sCFWUT",
      "created_at": "Sat Feb 08 05:17:41 +0000 2025",
      "retweet": 0,
      "likes": 1
    },
    {
      "tweet_count": 76,
      "username": "Crypto-Trading📊",
      "text": "Boom! Primal nailed it—called $HBAR and we’re up 160 % ! Wanna get in on the next big move ? Join us now Try it FREE for 14 days . Don’t miss your shot !  - https://t.co/2irlv0fhB4 - Get in now! \n\n$LINK $ETH $SOL $PEPE $ADA $BTC $TRUMP $MNT $USDC $SUI https://t.co/IQ9ygXUGS2",
      "created_at": "Sat Feb 08 02:40:21 +0000 2025",
      "retweet": 0,
      "likes": 1
    },
    {
      "tweet_count": 77,
      "username": "Crypto-Trading📊",
      "text": "Champ! Incredible wins ! 3 , 9 4 0.69 % on $TRUMPOFFICIAL ! Want to see similar results ? Jump in with a 14 day FREE Trial!  - https://t.co/2irlv0fhB4 - Be involved!\n\n $BTC $LINK $TRUMP $SUI $MNT $DOGE $SOL $USDC $ETH $PEPE https://t.co/8zJHDR1OYK",
      "created_at": "Sat Feb 08 02:40:01 +0000 2025",
      "retweet": 0,
      "likes": 0
    },
    {
      "tweet_count": 78,
      "username": "Crypto-Trading📊",
      "text": "It's Fab! Our junior analyst just saw 2 7 9 0.55 % on $BTC ! Want results like this ? Start your 14 -DAY FREE trial today ! !  - https://t.co/2irlv0fhB4 - Get started!\n\n $SUI $ETH $USDC $BTC $PEPE $LINK $SOL $ONDO $DOGE $XRP https://t.co/q5pwaWzVbd",
      "created_at": "Sat Feb 08 02:39:42 +0000 2025",
      "retweet": 0,
      "likes": 0
    },
    {
      "tweet_count": 79,
      "username": "Crypto-Trading📊",
      "text": "Zippy! Amazing return ! Our new member turned 2 5 3 0.39 % profit on $ETH ! Don t miss out – start your FREE 14 -DAY trial today and get insider market tips !  - https://t.co/2irlv0fhB4 - Stay with us! \n\n$XRP $ADA $ETH $USDC $SOL $MNT $BTC $LTC $PEPE $DOGE https://t.co/STSu2NGkUL",
      "created_at": "Sat Feb 08 02:39:24 +0000 2025",
      "retweet": 0,
      "likes": 0
    },
    {
      "tweet_count": 80,
      "username": "Crypto-Trading📊",
      "text": "It's Amazing! Our new member just bagged a massive 3 3 6 0.19 % on $HBAR ! Ready to make your move ? Get started with a 14 -DAY FREE trial ! !  - https://t.co/2irlv0fhB4 - Be part now! \n\n$ONDO $PEPE $BTC $ETH $SOL $DOGE $SUI $ADA $USDC $XRP https://t.co/E3dQXX5Qdg",
      "created_at": "Sat Feb 08 02:39:02 +0000 2025",
      "retweet": 0,
      "likes": 0
    },
    {
      "tweet_count": 81,
      "username": "Crypto-Trading📊",
      "text": "It's Zinging! Just bagged a 133 % gain on $GRIFFAIN ! Want in on the action ? Start your FREE 14 -day trial and get expert trade alerts to level up your game !  - https://t.co/2irlv0fhB4 - Make the move!\n\n $TRUMP $LTC $USDC $ONDO $ADA $SOL $DOGE $PEPE $ETH $BTC https://t.co/fno2o1rwYQ",
      "created_at": "Sat Feb 08 02:38:44 +0000 2025",
      "retweet": 0,
      "likes": 0
    },
    {
      "tweet_count": 82,
      "username": "Crypto-Trading📊",
      "text": "It's Upbeat! Our newest member bagged 1 3 8 0.6 % with $SPX ! Start your 14 -day FREE trial now and make your own wins ! !  - https://t.co/2irlv0fhB4 - Get your spot! $MNT $TRUMP $PEPE $ETH $LTC $SOL $ONDO $BTC $USDC $DOGE https://t.co/4cYdRnO8t9",
      "created_at": "Sat Feb 08 02:37:59 +0000 2025",
      "retweet": 0,
      "likes": 0
    },
    {
      "tweet_count": 83,
      "username": "Crypto-Trading📊",
      "text": "Nice! One of our members made an impressive 4 2 0.86 % return on $SOL ! Don’t wait – get your FREE 14 -DAY trial and start trading like a pro ! !  - https://t.co/2irlv0fhB4 - Be involved! \n\n$SUI $ETH $ONDO $LINK $BTC $PEPE $MNT $USDC $SOL $ADA https://t.co/4DoOYPE1Aq",
      "created_at": "Sat Feb 08 02:37:10 +0000 2025",
      "retweet": 0,
      "likes": 0
    },
    {
      "tweet_count": 84,
      "username": "Crypto-Trading📊",
      "text": "Hooray! Join us now for $38 only : Insane gains ! ( Your link ) Our analyst just pulled a Massive 230 % profits on $NEIROETH . Want in ? Hit up a 14 day FREE Trial!  - https://t.co/2irlv0fhB4 - Be a part! \n\n$SOL $ETH $BTC $TRUMP $LTC $USDC $MNT $PEPE $DOGE $ADA https://t.co/693zYzOLXZ",
      "created_at": "Sat Feb 08 02:35:39 +0000 2025",
      "retweet": 0,
      "likes": 1
    },
    {
      "tweet_count": 85,
      "username": "Crypto-Trading📊",
      "text": "Kudos! One of our members just earned an amazing 8 , 7 4 2 0.3 % return on $TRUMP ! Ready to achieve similar success ? Join us now and get a 14 -DAY FREE trial !  - https://t.co/2irlv0fhB4 - Don't wait!\n\n $XRP $BTC $USDC $ETH $PEPE $MNT $SOL $LTC $ADA $TRUMO https://t.co/0r2KEFqm3o",
      "created_at": "Sun Feb 09 13:23:30 +0000 2025",
      "retweet": 0,
      "likes": 0
    },
    {
      "tweet_count": 86,
      "username": "Crypto-Trading📊",
      "text": "It's Poppy! Unbelievable ! Our new member achieved 1 1 4 0.57 % on $AIXBT ! Don’t miss out—start your FREE trial today for exclusive alerts and tips ! !  - https://t.co/2irlv0fhB4 - Try it out! \n\n$ADA $SUI $DOGE $XRP $BTC $MNT $SOL $ETH $USDC $PEPE https://t.co/R8yfXMtjXk",
      "created_at": "Sun Feb 09 09:38:07 +0000 2025",
      "retweet": 0,
      "likes": 0
    },
    {
      "tweet_count": 87,
      "username": "Crypto-Trading📊",
      "text": "Wow! Our member just earned an incredible 2 6 0.41 % profit on $MDOGS ! Want in ? Start your 14 -DAY FREE trial now ! !  - https://t.co/2irlv0fhB4 - Claim your spot! \n\n$PEPE $TRUMO $LTC $BTC $SOL $MNT $ADA $USDC $ETH $DOGE https://t.co/qYxxYP0MNT",
      "created_at": "Sun Feb 09 09:33:29 +0000 2025",
      "retweet": 0,
      "likes": 0
    },
    {
      "tweet_count": 88,
      "username": "Crypto-Trading📊",
      "text": "It's a Bliss! Our analyst just made a 1 5 2 0.4 % gain on $VINE ! Don’t sit back—get your FREE 14 -day trial today and start winning ! !  -  https://t.co/2irlv0fhB4 - Join us!\n\n $DOGE $ONDO $BTC $LTC $SOL $MNT $ADA $ETH $PEPE $USDC https://t.co/FTxosYSCNu",
      "created_at": "Sun Feb 09 09:32:19 +0000 2025",
      "retweet": 0,
      "likes": 0
    },
    {
      "tweet_count": 89,
      "username": "Crypto-Trading📊",
      "text": "Hooray! Our newest member just crushed it with 2 8 0.49 % profit on $ETH ! Ready to start winning too ? Claim your 14 -DAY FREE trial now ! !  - https://t.co/2irlv0fhB4 - Take the leap!\n\n $MNT $ETH $USDC $DOGE $PEPE $XRP $ADA $BTC $SUI $SOL https://t.co/K4YxTfyswl",
      "created_at": "Sun Feb 09 09:31:26 +0000 2025",
      "retweet": 0,
      "likes": 0
    },
    {
      "tweet_count": 90,
      "username": "Crypto-Trading📊",
      "text": "It's Incredible! A member just achieved 1 5 6 0.22 % profit on $BTC ! Start your 14 -DAY FREE trial today to get in on the action ! !  - https://t.co/2irlv0fhB4 - Join us! \n\n$USDC $ETH $PEPE $DOGE $ONDO $ADA $BTC $SOL $TRUMO $SUI https://t.co/S4E8xH3CrI",
      "created_at": "Sun Feb 09 09:30:34 +0000 2025",
      "retweet": 0,
      "likes": 2
    },
    {
      "tweet_count": 91,
      "username": "Crypto-Trading📊",
      "text": "Just another day! Another member just earned 7 7 .75 % return on $ETH ! Ready to join the winning team ? Get your 14 -DAY FREE trial now ! !  - https://t.co/2irlv0fhB4 - Go for it! \n\n$XRP $MNT $ETH $SOL $ADA $PEPE $DOGE $ONDO $BTC $USDC https://t.co/zqhJKLBhxr",
      "created_at": "Sun Feb 09 09:02:31 +0000 2025",
      "retweet": 0,
      "likes": 2
    },
    {
      "tweet_count": 92,
      "username": "Crypto-Trading📊",
      "text": "It's Awesome! A member just hit 1 2 3 0.91 % profit on $MOODENG ! Want to follow their lead ? Sign up for a 14 -DAY FREE trial now ! !  - https://t.co/2irlv0fhB4 - Join right in!\n\n $PEPE $LTC $ETH $MNT $BTC $TRUMO $XRP $ONDO $SOL $USDC https://t.co/Qo9kav6nOU",
      "created_at": "Sun Feb 09 08:58:43 +0000 2025",
      "retweet": 0,
      "likes": 0
    },
    {
      "tweet_count": 93,
      "username": "Crypto-Trading📊",
      "text": "It's Buzzing! Yo , massive W secured ! Just ran up a 253 % gain on $DOGE—big ups to the team and the brainiacs who called it . Let’s keep the grind strong !  - https://t.co/2irlv0eJLw - Join us! \n\n$BTC $PEPE $XRP $ADA $MNT $SUI $USDC $SOL $ETH $DOGE https://t.co/eiVoH2qMLG",
      "created_at": "Sun Feb 09 08:57:52 +0000 2025",
      "retweet": 0,
      "likes": 0
    },
    {
      "tweet_count": 94,
      "username": "Crypto-Trading📊",
      "text": "Hippy! Our newest member bagged 1 3 8 0.6 % with $SPX ! Start your 14 -day FREE trial now and make your own wins ! !  - https://t.co/2irlv0fhB4 - Join now! \n\n$MNT $TRUMO $ADA $DOGE $USDC $XRP $PEPE $ETH $BTC $SOL https://t.co/XLDJq17bFd",
      "created_at": "Sun Feb 09 08:57:34 +0000 2025",
      "retweet": 0,
      "likes": 2
    },
    {
      "tweet_count": 95,
      "username": "Crypto-Trading📊",
      "text": "High-five! One member soared 1 3 7 0.21 % on $ZEREBRO ! Don’t miss out— Start your 14 -day FREE trial and unlock your potential today ! !  - https://t.co/2irlv0fhB4 - Be included! \n\n$ADA $PEPE $MNT $SOL $TRUMO $BTC $DOGE $XRP $ETH $USDC https://t.co/yg1tBr8VpC",
      "created_at": "Sun Feb 09 08:57:16 +0000 2025",
      "retweet": 0,
      "likes": 0
    },
    {
      "tweet_count": 96,
      "username": "Crypto-Trading📊",
      "text": "Hippy! A member just bagged 5 .94 % on $ETH ! Ready for success ? Start your 14 -day FREE trial and get expert alerts today ! !  - https://t.co/2irlv0eJLw - Sign up! \n\n$PEPE $MNT $SOL $ADA $XRP $USDC $LTC $ONDO $BTC $ETH https://t.co/yyEmTIu1yu",
      "created_at": "Sun Feb 09 08:55:28 +0000 2025",
      "retweet": 0,
      "likes": 1
    },
    {
      "tweet_count": 97,
      "username": "Crypto-Trading📊",
      "text": "It's Awesome! Yo , we just bagged 81 % on $SOL ! Got in at $ 1 9 0.82 , dipped out at $ 2  - https://t.co/2irlv0fhB4 - Join for moves! \n\n$MNT $SUI $LTC $DOGE $SOL $BTC $ETH $PEPE $TRUMO $USDC https://t.co/e8UedDuhH5",
      "created_at": "Sun Feb 09 08:54:56 +0000 2025",
      "retweet": 0,
      "likes": 2
    },
    {
      "tweet_count": 98,
      "username": "Crypto-Trading📊",
      "text": "Yippee! Yo , we just bagged 81 % on $SOL ! Got in at $ 1 9 0.82 , dipped out at $ 2  - https://t.co/2irlv0fhB4 - Be engaged! \n\n$BTC $SUI $MNT $PEPE $XRP $SOL $USDC $DOGE $LTC $ETH https://t.co/QSFRhdgdts",
      "created_at": "Sun Feb 09 06:21:55 +0000 2025",
      "retweet": 0,
      "likes": 0
    },
    {
      "tweet_count": 99,
      "username": "Crypto-Trading📊",
      "text": "Hooray! insane gains today ! Our analyst just pulled a huge 270 % profit on $XRP . You down to join ? Grab a 14 -DAY FREE trial and let’s level up  - https://t.co/2irlv0fhB4 - Act with us!\n\n $MNT $ONDO $USDC $XRP $SUI $BTC $LTC $SOL $ETH $PEPE https://t.co/51w7xz0pWp",
      "created_at": "Sun Feb 09 06:20:55 +0000 2025",
      "retweet": 0,
      "likes": 2
    },
    {
      "tweet_count": 100,
      "username": "Crypto-Trading📊",
      "text": "It's Amazing! Our senior analyst Jodez  just achieved 1 , 9 2 5 0.63 % profit on $VIRTUAL ! Ready to see similar results ? Start your 14 -DAY FREE trial today !  - https://t.co/2irlv0fhB4 - Be part now! \n\n$XRP $DOGE $SOL $PEPE $ONDO $ETH $BTC $ADA $USDC $MNT https://t.co/GgVTdBnhQE",
      "created_at": "Sun Feb 09 06:17:57 +0000 2025",
      "retweet": 0,
      "likes": 0
    },
    {
      "tweet_count": 101,
      "username": "Crypto-Trading📊",
      "text": "Bingo! One of our members made an impressive 4 2 0.86 % return on $SOL ! Don’t wait – get your FREE 14 -DAY trial and start trading like a pro ! !  - https://t.co/2irlv0fhB4 - Claim your spot!\n\n $MNT $PEPE $XRP $USDC $ONDO $LTC $SUI $SOL $BTC $ETH https://t.co/zAwIdfb0T8",
      "created_at": "Sun Feb 09 06:16:50 +0000 2025",
      "retweet": 0,
      "likes": 1
    },
    {
      "tweet_count": 102,
      "username": "Crypto-Trading📊",
      "text": "Cheers! Our expert analyst turned 7 4 .20 % profit on $COOKIE ! Take action today for a 14 -DAY FREE trial and unlock insider signals ! !  - https://t.co/2irlv0fhB4 - Be part! \n\n$SUI $ONDO $DOGE $TRUMP $ETH $USDC $ADA $SOL $PEPE $BTC https://t.co/B0xk1LX3p6",
      "created_at": "Sun Feb 09 04:45:49 +0000 2025",
      "retweet": 0,
      "likes": 0
    },
    {
      "tweet_count": 103,
      "username": "Crypto-Trading📊",
      "text": "Bingo! One of our members made an impressive 4 2 0.86 % return on $SOL ! Don’t wait – get your FREE 14 -DAY trial and start trading like a pro ! !  - https://t.co/2irlv0fhB4 - Claim your spot!\n\n $MNT $PEPE $XRP $USDC $ONDO $LTC $SUI $SOL $BTC $ETH https://t.co/TvNPafvm2y",
      "created_at": "Sun Feb 09 04:45:06 +0000 2025",
      "retweet": 0,
      "likes": 0
    },
    {
      "tweet_count": 104,
      "username": "Crypto-Trading📊",
      "text": "Yippee! Yo , we just bagged 81 % on $SOL ! Got in at $ 1 9 0.82 , dipped out at $ 2  - https://t.co/2irlv0fhB4 - Be engaged! \n\n$BTC $SUI $MNT $PEPE $XRP $SOL $USDC $DOGE $LTC $ETH https://t.co/Ee6yNr0ueV",
      "created_at": "Sun Feb 09 04:41:08 +0000 2025",
      "retweet": 0,
      "likes": 0
    },
    {
      "tweet_count": 105,
      "username": "Crypto-Trading📊",
      "text": "It's a day! One of our members just earned an amazing 8 , 7 4 2 0.3 % return on $TRUMP ! Ready to achieve similar success ? Join us now and get a 14 -DAY FREE trial !  - https://t.co/2irlv0fhB4 - Don't wait! \n\n$ETH $ONDO $BTC $ADA $USDC $SUI $SOL $MNT $PEPE $DOGE https://t.co/0qrl0ow5iq",
      "created_at": "Sun Feb 09 04:40:47 +0000 2025",
      "retweet": 0,
      "likes": 1
    },
    {
      "tweet_count": 106,
      "username": "Crypto-Trading📊",
      "text": "Hooray! insane gains today ! Our analyst just pulled a huge 270 % profit on $XRP . You down to join ? Grab a 14 -DAY FREE trial and let’s level up  - https://t.co/2irlv0eJLw - Act with us! \n\n$MNT $ONDO $USDC $XRP $SUI $BTC $LTC $SOL $ETH $PEPE https://t.co/xtI1CSxcJI",
      "created_at": "Sun Feb 09 04:40:28 +0000 2025",
      "retweet": 0,
      "likes": 0
    },
    {
      "tweet_count": 107,
      "username": "Crypto-Trading📊",
      "text": "Yippee! One of our members just made an incredible 1 7 1 0.5 % profit on $1000APU ! Want to see similar results ? Sign up now for a 14 -DAY FREE trial ! !  - https://t.co/2irlv0fhB4 - You can do! \n\n$LTC $ONDO $SOL $DOGE $BTC $MNT $XRP $USDC $ETH $PEPE https://t.co/RQyhcsghvi",
      "created_at": "Sun Feb 09 04:40:06 +0000 2025",
      "retweet": 0,
      "likes": 0
    },
    {
      "tweet_count": 108,
      "username": "Crypto-Trading📊",
      "text": "Just Rolling! Incredible Win ! Member achieved 8 3 6 0.54 % on $BTC ! Try our 14 -day FREE trial and start generating massive returns now ! !  - https://t.co/2irlv0fhB4 - Now or never! \n\n$ETH $MNT $PEPE $USDC $XRP $ONDO $DOGE $TRUMP $BTC $SOL https://t.co/dpwk67c1aS",
      "created_at": "Sun Feb 09 04:39:04 +0000 2025",
      "retweet": 0,
      "likes": 1
    },
    {
      "tweet_count": 109,
      "username": "Crypto-Trading📊",
      "text": "It Sparked! Primal , our top trader , who just made a massive 4 0.96 % profit on $PUMPAI ! Want to see results like this ? Start your 14 -DAY FREE trial today  - https://t.co/2irlv0fhB4 - Try for free! \n\n$SOL $ETH $TRUMO $USDC $LTC $MNT $PEPE $ONDO $XRP $BTC https://t.co/MiXBtHl637",
      "created_at": "Sun Feb 09 04:29:29 +0000 2025",
      "retweet": 0,
      "likes": 1
    },
    {
      "tweet_count": 110,
      "username": "Crypto-Trading📊",
      "text": "Yippee! Yo , we just bagged 81 % on $SOL ! Got in at $ 1 9 0.82 , dipped out at $ 2  - https://t.co/2irlv0fhB4 - Be engaged! \n\n$BTC $SUI $MNT $PEPE $XRP $SOL $USDC $DOGE $LTC $ETH https://t.co/8REyBsXLsA",
      "created_at": "Sun Feb 09 04:28:52 +0000 2025",
      "retweet": 0,
      "likes": 0
    },
    {
      "tweet_count": 111,
      "username": "Crypto-Trading📊",
      "text": "It's a day! One of our members just earned an amazing 8 , 7 4 2 0.3 % return on $TRUMP ! Ready to achieve similar success ? Join us now and get a 14 -DAY FREE trial !  - https://t.co/2irlv0fhB4 - Don't wait!\n\n $ETH $ONDO $BTC $ADA $USDC $SUI $SOL $MNT $PEPE $DOGE https://t.co/NX6lps9LzS",
      "created_at": "Sun Feb 09 04:28:34 +0000 2025",
      "retweet": 0,
      "likes": 0
    },
    {
      "tweet_count": 112,
      "username": "Crypto-Trading📊",
      "text": "It's pure Joy! Primal nailed it—called $HBAR and we’re up 160 % ! Wanna get in on the next big move ? Join us now Try it FREE for 14 days . Don’t miss your shot !  - https://t.co/2irlv0fhB4 - Join quickly! \n\n$ETH $SOL $XRP $PEPE $ADA $ONDO $USDC $DOGE $LTC $BTC https://t.co/xBFSYtRj4M",
      "created_at": "Sun Feb 09 04:27:55 +0000 2025",
      "retweet": 0,
      "likes": 3
    },
    {
      "tweet_count": 113,
      "username": "Crypto-Trading📊",
      "text": "It's Flowing! A member just achieved 1 5 6 0.22 % profit on $BTC ! Start your 14 -DAY FREE trial today to get in on the action ! !  - https://t.co/2irlv0fhB4 - Be part! \n\n$BTC $ETH $SOL $TRUMO $LTC $USDC $SUI $DOGE $ONDO $PEPE https://t.co/sRrZzk0D06",
      "created_at": "Mon Feb 10 05:43:21 +0000 2025",
      "retweet": 0,
      "likes": 0
    },
    {
      "tweet_count": 114,
      "username": "Crypto-Trading📊",
      "text": "It's Super! Big gains today ! Our new member made a 7 9 8 0.93 % profit on $AAVE ! Join us and start your 14 -DAY FREE trial today !  - https://t.co/2irlv0fhB4 - Make the move!\n\n $XRP $ETH $SOL $MNT $ADA $LTC $PEPE $USDC $TRUMO $BTC https://t.co/nLZB4huPRL",
      "created_at": "Mon Feb 10 05:42:58 +0000 2025",
      "retweet": 0,
      "likes": 0
    },
    {
      "tweet_count": 115,
      "username": "Crypto-Trading📊",
      "text": "Victory! Our member made an incredible 1 5 7 0.67 % profit on $AAVE ! Ready to level up ? Start your FREE 14 -day trial now ! !  - https://t.co/2irlv0fhB4 - Take action! \n\n$LTC $ONDO $SOL $BTC $MNT $PEPE $DOGE $ETH $USDC $ADA https://t.co/omBcVFvH1U",
      "created_at": "Mon Feb 10 05:42:37 +0000 2025",
      "retweet": 0,
      "likes": 1
    },
    {
      "tweet_count": 116,
      "username": "Crypto-Trading📊",
      "text": "Just Bright! Our member just locked in a 2 3 0.75 % return on $VINE ! Ready to join ? Start your FREE 14 -day trial today ! !  - https://t.co/2irlv0fhB4 - Get in now! \n\n$BTC $USDC $SUI $XRP $PEPE $ETH $MNT $DOGE $LTC $SOL https://t.co/k4MwCltu5I",
      "created_at": "Mon Feb 10 05:42:08 +0000 2025",
      "retweet": 0,
      "likes": 0
    },
    {
      "tweet_count": 117,
      "username": "Crypto-Trading📊",
      "text": "It's a Delight! A member just made 1 6 0.26 % profit from $BUTTHOLE ! Want in ? Get your 14 -day FREE trial today ! !  - https://t.co/2irlv0eJLw - Be part now! \n\n$PEPE $LTC $TRUMO $MNT $ETH $BTC $USDC $SOL $ONDO $DOGE https://t.co/xGuRkFx2YF",
      "created_at": "Mon Feb 10 05:41:46 +0000 2025",
      "retweet": 0,
      "likes": 0
    },
    {
      "tweet_count": 118,
      "username": "Crypto-Trading📊",
      "text": "Just Bright! Our junior trader Jafar just made a massive 5 2 5 0.03 % profit on $MELANIA ! Want in ? Start your 14 -DAY FREE trial now ! !  - https://t.co/2irlv0fhB4 - Don't wait! \n\n$ADA $MNT $XRP $LTC $USDC $SUI $ETH $PEPE $BTC $SOL https://t.co/T9K2i1NOWN",
      "created_at": "Mon Feb 10 05:40:26 +0000 2025",
      "retweet": 0,
      "likes": 0
    },
    {
      "tweet_count": 119,
      "username": "Crypto-Trading📊",
      "text": "It's Exuberant! Primal , our top trader , for making an insane 1 4 1 0.12 % profit on $TOSHI ! Ready to level up ? Start your 14 -DAY FREE trial now  - https://t.co/2irlv0fhB4 - Join it now!\n\n $BTC $ADA $ETH $MNT $SOL $XRP $USDC $ONDO $DOGE $PEPE https://t.co/iNA6B5XLqQ",
      "created_at": "Mon Feb 10 05:39:59 +0000 2025",
      "retweet": 0,
      "likes": 0
    },
    {
      "tweet_count": 120,
      "username": "Crypto-Trading📊",
      "text": "Booyah! Another member made 283 % profit on $VINE ! Sign up today for a 14 -DAY FREE trial and start receiving expert trade tips ! !  -https://t.co/2irlv0fhB4 - Click here!\n\n $ADA $LTC $SOL $ONDO $PEPE $USDC $TRUMO $DOGE $ETH $BTC https://t.co/Sw3Y6XT8G6",
      "created_at": "Mon Feb 10 05:39:13 +0000 2025",
      "retweet": 0,
      "likes": 0
    }
  ]
}